{"header":{"lv":0,"type":1,"star1":2,"star2":3,"star3":4,"totol":5,"balls":6,"items":7,"isAdvanceSmall":8},"data":["19",1,0,1593,3225,0,50,[{"offX":0,"offY":1,"type":2,"info":3},[2,5,1,{"num":44}],[3,5,1,{"num":44}],[7,5,1,{"num":44}],[8,5,1,{"num":44}],[10,5,1,{"num":44}],[5,5,1,{"num":44}],[1,6,1,{"num":80}],[1,7,1,{"num":50}],[3,7,1,{"num":50}],[5,7,1,{"num":50}],[7,7,1,{"num":50}],[8,7,1,{"num":50}],[9,7,1,{"num":50}],[1,8,1,{"num":60}],[9,8,1,{"num":60}],[1,9,1,{"num":60}],[9,9,1,{"num":60}],[1,10,1,{"num":50}],[2,10,1,{"num":50}],[3,10,1,{"num":50}],[7,10,1,{"num":50}],[9,10,1,{"num":50}],[9,11,1,{"num":40}],[0,12,1,{"num":30}],[1,12,1,{"num":30}],[2,12,1,{"num":30}],[3,12,1,{"num":30}],[7,12,1,{"num":30}],[8,12,1,{"num":30}],[2,7,24,{"isClockDir":false}],[0,6,38,{}],[9,12,1,{"num":30}],[1,5,1,{"num":44}],[8,10,24,{}],[5,10,1,{"num":50}],[5,12,1,{"num":30}],[9,5,1,{"num":44}],[3,8,23,{"addBall":2,"num":20}],[3,9,23,{"addBall":2,"num":20}],[7,8,23,{"addBall":2,"num":20}],[7,9,23,{"addBall":2,"num":20}],[4,12,9,{"isOpen":false,"num":12}],[6,12,9,{"isOpen":false,"num":12}],[4,10,9,{"isOpen":false,"num":12}],[6,10,9,{"isOpen":false,"num":12}],[4,7,9,{"num":12}],[6,7,9,{"num":12}],[4,5,9,{"num":11}],[6,5,9,{"num":11}],[2,11,8,{}],[3,6,8,{}],[4,11,8,{}],[5,6,8,{}],[6,11,8,{}],[7,6,8,{}]],false]}